cli/__init__.py
cli/main.py
cli/installer/__init__.py
cli/installer/agents.py
cli/installer/config_writers.py
cli/installer/env_writer.py
cli/installer/ui.py
cli/installer/uv_manager.py
cli/installer/wizard.py
config/__init__.py
config/defaults.py
config/llm.py
logging_utils/__init__.py
logging_utils/config.py
logging_utils/formatter.py
logging_utils/handlers.py
logging_utils/logger.py
tools/__init__.py
tools/a11_tool_context.md
tools/base.py
tools/a11y_audit/__init__.py
tools/a11y_audit/domains.py
tools/a11y_audit/finding.py
tools/a11y_audit/guidance.py
tools/a11y_audit/report.py
tools/a11y_audit/severity.py
tools/a11y_audit/tool.py
tools/a11y_audit/wcag.py
tools/dashboard/__init__.py
tools/dashboard/handlers.py
tools/dashboard/models.py
tools/dashboard/server.py
tools/dashboard/websocket.py
tools/dashboard/static/css/dashboard.css
tools/dashboard/static/icons/a11y.svg
tools/dashboard/static/icons/accessibility.svg
tools/dashboard/static/icons/devops.svg
tools/dashboard/static/icons/file.svg
tools/dashboard/static/icons/folder-open.svg
tools/dashboard/static/icons/folder.svg
tools/dashboard/static/icons/principal.svg
tools/dashboard/static/icons/reports.svg
tools/dashboard/static/icons/security.svg
tools/dashboard/static/icons/settings.svg
tools/dashboard/static/js/dashboard.js
tools/dashboard/templates/index.html
tools/dashboard_info/__init__.py
tools/dashboard_info/core.py
tools/devops_audit/__init__.py
tools/devops_audit/domains.py
tools/devops_audit/finding.py
tools/devops_audit/guidance.py
tools/devops_audit/report.py
tools/devops_audit/severity.py
tools/devops_audit/tool.py
tools/devops_audit/validation.py
tools/expert_analysis/__init__.py
tools/expert_analysis/confidence_utils.py
tools/expert_analysis/consensus.py
tools/expert_analysis/prompt_templates.py
tools/expert_analysis/service.py
tools/generate_report/__init__.py
tools/generate_report/file_operations.py
tools/generate_report/models.py
tools/generate_report/numbering.py
tools/generate_report/tool.py
optix_mcp_server-1.0.0.dist-info/METADATA
optix_mcp_server-1.0.0.dist-info/WHEEL
optix_mcp_server-1.0.0.dist-info/entry_points.txt
optix_mcp_server-1.0.0.dist-info/RECORD
