Metadata-Version: 2.4
Name: optix-mcp-server
Version: 1.0.0
Summary: MCP server for source code analysis
Author: optix-mcp-server contributors
License: MIT
Requires-Python: >=3.10
Requires-Dist: mcp[cli]>=1.25.0
Requires-Dist: python-dotenv>=1.0.0
Requires-Dist: questionary>=2.0.0
Requires-Dist: rich>=13.0.0
Requires-Dist: websockets>=12.0
Provides-Extra: dev
Requires-Dist: pytest-asyncio>=0.21.0; extra == 'dev'
Requires-Dist: pytest>=7.0; extra == 'dev'
Provides-Extra: llm
Requires-Dist: openai>=1.0.0; extra == 'llm'
Provides-Extra: openai
Requires-Dist: openai>=1.0.0; extra == 'openai'
